qtorch/__init__.py
qtorch/number.py
qtorch/auto_low/__init__.py
qtorch/auto_low/auto_low.py
qtorch/optim/__init__.py
qtorch/optim/optim_low.py
qtorch/quant/__init__.py
qtorch/quant/quant_function.py
qtorch/quant/quant_module.py
qtorch/quant/quant_cpu/bit_helper.cpp
qtorch/quant/quant_cpu/quant_cpu.cpp
qtorch/quant/quant_cpu/quant_cpu.h
qtorch/quant/quant_cpu/sim_helper.cpp
qtorch/quant/quant_cuda/bit_helper.cu
qtorch/quant/quant_cuda/block_kernel.cu
qtorch/quant/quant_cuda/fixed_point_kernel.cu
qtorch/quant/quant_cuda/float_kernel.cu
qtorch/quant/quant_cuda/quant.cu
qtorch/quant/quant_cuda/quant_cuda.cpp
qtorch/quant/quant_cuda/quant_cuda.h
qtorch/quant/quant_cuda/quant_kernel.h
qtorch/quant/quant_cuda/sim_helper.cu
qtorch-0.3.0.dist-info/LICENSE
qtorch-0.3.0.dist-info/METADATA
qtorch-0.3.0.dist-info/WHEEL
qtorch-0.3.0.dist-info/top_level.txt
qtorch-0.3.0.dist-info/RECORD
